parsuricata/__init__.py
parsuricata/_parser.py
parsuricata/rules.py
parsuricata/transformer.py
parsuricata-0.4.0.dist-info/LICENSE
parsuricata-0.4.0.dist-info/METADATA
parsuricata-0.4.0.dist-info/WHEEL
parsuricata-0.4.0.dist-info/RECORD
