Metadata-Version: 2.1
Name: parsuricata
Version: 0.4.0
Summary: Parse Suricata rules
Home-page: https://github.com/theY4Kman/parsuricata
License: MIT
Keywords: suricata,security
Author: Zach "theY4Kman" Kanzler
Author-email: they4kman@gmail.com
Requires-Python: >=3.6,<4.0
Classifier: License :: OSI Approved :: MIT License
Classifier: Programming Language :: Python :: 3
Classifier: Programming Language :: Python :: 3.6
Classifier: Programming Language :: Python :: 3.7
Classifier: Programming Language :: Python :: 3.8
Classifier: Programming Language :: Python :: 3.9
Classifier: Programming Language :: Python :: 3.10
Classifier: Programming Language :: Python :: 3.11
Requires-Dist: lark-parser (>=0.12.0,<0.13.0)
Project-URL: Issues, https://github.com/theY4Kman/parsuricata/issues
Project-URL: Repository, https://github.com/theY4Kman/parsuricata
